{"altmetric_id":3756078,"counts":{"readers":{"mendeley":11,"citeulike":0,"connotea":0},"blogs":{"unique_users_count":3,"unique_users":[659,52467,58234],"posts_count":3},"news":{"unique_users_count":1,"unique_users":["scitech_daily"],"posts_count":1},"total":{"posts_count":15},"twitter":{"unique_users_count":11,"unique_users":["StarshipBuilder","AstroPHYPapers","michael_w_busch","blobrana","megschwamb","astro_ph_","ProfAbelMendez","luinily","AstroBioProf","KLlewellin","BaronianConsult"],"posts_count":11}},"selected_quotes":["Discovery of the 2nd planetary system with 4 stars - Roberts et al. in press","Know the Star, Know the Planet. III. Discovery of Late-Type Companions to Two #Exoplanets Host Stars See"],"citation":{"altmetric_jid":"arxiv","arxiv_id":"1503.01211","first_seen_on":"2015-03-05T02:19:51+00:00","issns":[],"journal":"arXiv","last_mentioned_on":1425818220,"links":["http:\/\/arxiv.org\/abs\/1503.01211","http:\/\/arxiv.org\/pdf\/1503.01211.pdf"],"pdf_url":"http:\/\/arxiv.org\/pdf\/1503.01211v1","pubdate":"2015-03-04T04:04:13+00:00","title":"Know the Star, Know the Planet. III. Discovery of Late-Type Companions\n\n  to Two Exoplanet Host Stars","type":"article","mendeley_url":"http:\/\/www.mendeley.com\/research\/know-star-know-planet-iii-discovery-latetype-companions-two-exoplanet-host-stars"},"altmetric_score":{"score":34.99,"score_history":{"1y":0,"6m":0,"3m":0,"1m":0,"1w":0,"6d":0,"5d":0,"4d":0,"3d":0,"2d":0,"1d":0,"at":34.99},"context_for_score":{"all":{"total_number_of_other_articles":5040289,"mean":5.9643426109799,"rank":134547,"this_scored_higher_than_pct":97,"this_scored_higher_than":4905118,"rank_type":"exact","sample_size":5040289,"percentile":97},"similar_age_3m":{"total_number_of_other_articles":149339,"mean":10.189683831309,"rank":8126,"this_scored_higher_than_pct":94,"this_scored_higher_than":141213,"rank_type":"exact","sample_size":149339,"percentile":94},"this_journal":{"total_number_of_other_articles":322948,"mean":2.2495484769947,"rank":2152,"this_scored_higher_than_pct":99,"this_scored_higher_than":320779,"rank_type":"exact","sample_size":322948,"percentile":99},"similar_age_this_journal_3m":{"total_number_of_other_articles":73,"mean":17.457166666667,"rank":10,"this_scored_higher_than_pct":86,"this_scored_higher_than":63,"rank_type":"exact","sample_size":73,"percentile":86}}},"demographics":{"poster_types":{"member_of_the_public":8,"researcher":3},"users":{"twitter":{"cohorts":{"Members of the public":9,"Scientists":2}},"mendeley":{"by_status":{"Professor > Associate Professor":1,"Researcher":2,"Student  > Ph. D. Student":3,"Other":1,"Student  > Bachelor":4},"by_discipline":{"Physics and Astronomy":11}}},"geo":{"twitter":{"US":2,"PR":1,"JP":1},"mendeley":{"CL":1,"DE":1}}},"posts":{"twitter":[{"url":"https:\/\/twitter.com\/StarshipBuilder\/status\/573306827015917568","license":"datasift","citation_ids":[3756078],"posted_on":"2015-03-05T02:19:33+00:00","author":{"name":"Starship Engineers","image":"https:\/\/pbs.twimg.com\/profile_images\/3081898813\/cacb86324b177beb102ff5091ad7ad92_normal.jpeg","description":"Where are we going? #exoplanets How will we get there? #StarshipCulture\nStarship Engineer for hire, inquire within...","id_on_source":"StarshipBuilder","tweeter_id":"1070695968","geo":{"lt":null,"ln":null},"followers":1692},"tweet_id":"573306827015917568"},{"url":"https:\/\/twitter.com\/AstroPHYPapers\/status\/573316877801271296","license":"datasift","citation_ids":[3756078],"posted_on":"2015-03-05T02:59:30+00:00","author":{"name":"Astrophysics Papers","url":"http:\/\/arxiv.org\/archive\/astro-ph","image":"https:\/\/pbs.twimg.com\/profile_images\/1149878727\/arxiv_normal.png","description":"New Astrophysics submissions to http:\/\/arxiv.org (not affiliated with http:\/\/arxiv.org)","id_on_source":"AstroPHYPapers","tweeter_id":"129992461","geo":{"lt":null,"ln":null},"followers":4754},"tweet_id":"573316877801271296"},{"url":"https:\/\/twitter.com\/michael_w_busch\/status\/573346261123792896","license":"datasift","rt":["megschwamb"],"citation_ids":[3756078],"posted_on":"2015-03-05T04:56:15+00:00","author":{"name":"Michael Busch","url":"http:\/\/www.seti.org\/users\/mbusch","image":"https:\/\/pbs.twimg.com\/profile_images\/559122605014130688\/Yltud6pR_normal.jpeg","description":"Planetary astronomer, currently based at the SETI Institute.  Drinker of tea.  Opinions expressed here are strictly my own.\n\nTo bigotry no sanction.","id_on_source":"michael_w_busch","tweeter_id":"1580467730","geo":{"lt":null,"ln":null},"followers":2225},"tweet_id":"573346261123792896"},{"url":"https:\/\/twitter.com\/blobrana\/status\/573358996565958656","license":"datasift","rt":["megschwamb"],"citation_ids":[3756078],"posted_on":"2015-03-05T05:46:51+00:00","author":{"name":"Blobrana","url":"http:\/\/astronomy.activeboard.com","image":"https:\/\/pbs.twimg.com\/profile_images\/778170705070481410\/AiVkpyvw_normal.jpg","description":"Astronomy news portal for info-maniacs.       The official blobrana twitter account.","id_on_source":"blobrana","tweeter_id":"14105953","geo":{"lt":null,"ln":null},"followers":1732},"tweet_id":"573358996565958656"},{"url":"https:\/\/twitter.com\/megschwamb\/status\/573332553588842496","license":"datasift","citation_ids":[3756078],"posted_on":"2015-03-05T04:01:47+00:00","author":{"name":"Meg Schwamb","url":"http:\/\/www.megschwamb.com","image":"https:\/\/pbs.twimg.com\/profile_images\/598501014673563648\/2n5L1Hpu_normal.jpg","description":"Planetary scientist, astronomer, Gemini North assistant scientist: KBOs, Planet Four(Mars), MBCs(Comet Hunters),LSST SSSC co-chair. Opinions tweeted are my own","id_on_source":"megschwamb","tweeter_id":"141628169","geo":{"lt":19.72972,"ln":-155.09,"country":"US"},"followers":3340},"tweet_id":"573332553588842496"},{"url":"https:\/\/twitter.com\/astro_ph_\/status\/573391872535601152","license":"datasift","citation_ids":[3756078],"posted_on":"2015-03-05T07:57:30+00:00","author":{"name":"arXiv astro-ph","image":"https:\/\/pbs.twimg.com\/profile_images\/587813332997902336\/tnud7Cy2_normal.png","description":"- New submissions in arXiv \/ - Updated around 01:00GMT \/ - See the following list for other categories","id_on_source":"astro_ph_","tweeter_id":"3060166303","geo":{"lt":null,"ln":null},"followers":259},"tweet_id":"573391872535601152"},{"url":"https:\/\/twitter.com\/ProfAbelMendez\/status\/573401099761156096","license":"datasift","citation_ids":[3756078],"posted_on":"2015-03-05T08:34:10+00:00","author":{"name":"Prof. Abel M\u00e9ndez","url":"http:\/\/phl.upr.edu","image":"https:\/\/pbs.twimg.com\/profile_images\/794360876706893824\/RWklsf_W_normal.jpg","description":"Planetary Astrobiologist and Director of the @PlanetaryHabLab. Studying habitable worlds in the universe.","id_on_source":"ProfAbelMendez","tweeter_id":"89264343","geo":{"lt":18.47244,"ln":-66.71573,"country":"PR"},"followers":12434},"tweet_id":"573401099761156096"},{"url":"https:\/\/twitter.com\/luinily\/status\/573466326624157696","license":"datasift","rt":["megschwamb"],"citation_ids":[3756078],"posted_on":"2015-03-05T12:53:21+00:00","author":{"name":"Yoann Coldefy","url":"http:\/\/plus.google.com\/116649936371258286955\/posts","image":"https:\/\/pbs.twimg.com\/profile_images\/574171874457821184\/f1e8Uad7_normal.jpeg","description":"\u539f\u767a\u53cd\u5bfe\u30fb\u6b7b\u5211\u53cd\u5bfe\n2008\u5e749\u6708\u6765\u65e5\u3001\u73fe\u5728\u6771\u4eac\u306b\u4f4f\u3093\u3067\u3044\u308b\u30d5\u30e9\u30f3\u30b9\u4eba\u306e\u30bd\u30d5\u30c8\u30a6\u30a7\u30a2\u958b\u767a\u6280\u8853\u8005\u3002\u8336\u9053\u3082\u5b66\u3093\u3067\u307e\u3059\uff01","id_on_source":"luinily","tweeter_id":"113025007","geo":{"lt":35.6895,"ln":139.69171,"country":"JP"},"followers":229},"tweet_id":"573466326624157696"},{"url":"https:\/\/twitter.com\/AstroBioProf\/status\/573488433202618368","license":"datasift","citation_ids":[3756078],"posted_on":"2015-03-05T14:21:12+00:00","author":{"name":"Harold Geller","url":"http:\/\/physics.gmu.edu\/~hgeller\/","image":"https:\/\/pbs.twimg.com\/profile_images\/455736734555205634\/5M7nPEU3_normal.jpeg","description":"Observatory Director (George Mason University) Astrosciences, science, education. NASA\/JPL Solar System Ambassador. Opinions are my own. Links not= endorsements","id_on_source":"AstroBioProf","tweeter_id":"21012557","geo":{"lt":38.84622,"ln":-77.30637,"country":"US"},"followers":15975},"tweet_id":"573488433202618368"},{"url":"https:\/\/twitter.com\/KLlewellin\/status\/573490460221665283","license":"datasift","rt":["AstroBioProf"],"citation_ids":[3756078],"posted_on":"2015-03-05T14:29:15+00:00","author":{"name":"K.Llewellin","url":"https:\/\/www.smashwords.com\/books\/view\/281515","image":"https:\/\/pbs.twimg.com\/profile_images\/3158555240\/8256d6f6c0774f4643592d7d2b3d731c_normal.png","description":"\ud83d\udc7d unappreciated #scifi #Indieauthor \ud83d\udc0b Unemployed cetologist @DolphinSeeker30 \ud83d\udc0d Slytherin \ud83c\udfae Gamer girl \ud83d\ude80geek \ud83d\udcda #ICT #OUStudent \ud83d\udcdd #AmWriting #AmEditing","id_on_source":"KLlewellin","tweeter_id":"960356022","geo":{"lt":null,"ln":null},"followers":1559},"tweet_id":"573490460221665283"},{"url":"https:\/\/twitter.com\/BaronianConsult\/status\/573610164642799616","license":"datasift","rt":["ProfAbelMendez"],"citation_ids":[3756078],"posted_on":"2015-03-05T22:24:55+00:00","author":{"name":"Baronian Consulting","image":"https:\/\/pbs.twimg.com\/profile_images\/344513261580112136\/1bef8d5247ba652c1f6a57a1311172d0_normal.jpeg","description":"Interested in Aerospace, Aviation,  Advanced Technologies, HealthCare Technologies, Competitive Intelligence, Human Capital Solutions","id_on_source":"BaronianConsult","tweeter_id":"1486117886","geo":{"lt":null,"ln":null},"followers":1494},"tweet_id":"573610164642799616"}],"blogs":[{"title":"Planet in a Quadruple Star System","url":"http:\/\/www.centauri-dreams.org\/?p=32684&utm_source=feedburner&utm_medium=feed&utm_campaign=Feed%3A+centauri-dreams%2Feepu+%28Centauri+Dreams%29","citation_ids":[3756078],"posted_on":"2015-03-05T17:30:00+00:00","summary":"Planets in multiple star systems intrigue us particularly when we try to imagine the view from the surface. Call it the &lsquo;Tatooine Effect,&rsquo; made to order for visual effects specialists and cinematographers. But planets like these also raise inte","author":{"name":"Centauri Dreams","url":"http:\/\/www.centauri-dreams.org\/","description":"The News Forum of the Tau Zero Foundation"}},{"title":"30 Ari Bb: Super-Jupiter Exoplanet Orbiting in Quadruple Star System","url":"http:\/\/www.sci-news.com\/astronomy\/science-30-ari-bb-super-jupiter-exoplanet-quadruple-star-system-02565.html","citation_ids":[3756078],"posted_on":"2015-03-05T17:55:00+00:00","summary":"According to a team of astronomers headed by Dr Lewis Roberts from NASA&rsquo;s Jet Propulsion Laboratory in Pasadena, an extrasolar gas giant called 30 Arietis Bb (30 Ari Bb) is the second known example of a planet residing in a system with four stars. Wh","author":{"name":"Sci-News.com","url":"http:\/\/www.sci-news.com","description":""}},{"title":"Deuxi\u00e8me cas d\u2019une plan\u00e8te dans un syst\u00e8me \u00e0 quatre \u00e9toiles","url":"http:\/\/www.gurumed.org\/2015\/03\/08\/deuxime-cas-dune-plante-dans-un-systme-quatre-toiles\/","citation_ids":[3756078],"posted_on":"2015-03-08T12:37:00+00:00","summary":"Guru Med\n\n\t\t\nLes astronomes ont d&eacute;couvert le second cas connu d&rsquo;une plan&egrave;te r&eacute;sidant dans un syst&egrave;me stellaire quadruple. La plan&egrave;te, d&eacute;sign&eacute;e 30 Ari Bb &eacute;tait d&eacute;j&agrave; connu, mais il &","author":{"name":"GuruMeditation","url":"http:\/\/www.gurumed.org\/","description":"Une fine s&eacute;lection et vulgarisation de l'Actualit&eacute;s des Sciences et des nouvelles Technologies"}}],"news":[{"title":"Astronomers Identify a Quadruple Star System, 30 Ari","url":"http:\/\/scitechdaily.com\/astronomers-identify-quadruple-star-system-30-ari\/","license":"public","citation_ids":[3754680,3756078],"posted_on":"2015-03-05T16:49:23+00:00","summary":"Using the Robo-AO adaptive optics system and the PALM-3000 adaptive optics system, astronomers have identified a planet in a quadruple star system for only the second time. Growing up as a planet with more than one parent star has its challenges. Though th","author":{"name":"Scitech Daily","url":"http:\/\/scitechdaily.com\/","image":"https:\/\/s3.amazonaws.com\/weyland.altmetric.com\/news_sources\/logos\/000\/000\/648\/normal\/image.png?1395834498"}}]}}