{"altmetric_id":4879243,"counts":{"readers":{"mendeley":1,"citeulike":0,"connotea":0},"total":{"posts_count":1},"blogs":{"unique_users_count":1,"unique_users":[52462],"posts_count":1}},"citation":{"altmetric_jid":"4f6fa4ef3cf058f610002cc7","authors":["Sandhya Sriram","Subha Subramanian","Prasanna Kumar Juvvuna","Craig McFarlane","Monica Senna Salerno","Ravi Kambadur","Mridula Sharma"],"doi":"10.1074\/jbc.a113.483115","first_seen_on":"2015-12-15T16:20:20+00:00","issns":["1083-351X"],"issue":"45","journal":"Journal of Biological Chemistry","last_mentioned_on":1450189800,"links":["http:\/\/www.jbc.org\/content\/290\/45\/27012.full?sid=6011cda8-8a91-42b8-ac16-60b95db60dda"],"pdf_url":"http:\/\/www.jbc.org\/content\/290\/45\/27012.full.pdf","pmid":"26546691","pubdate":"2015-11-06T00:00:00+00:00","publisher_subjects":[{"name":"Biological Sciences","scheme":"era"},{"name":"Medical And Health Sciences","scheme":"era"},{"name":"Chemical Sciences","scheme":"era"}],"scopus_subjects":["Life Sciences","Biochemistry, Genetics and Molecular Biology"],"subjects":["biochemistry"],"title":"Myostatin induces DNA damage in skeletal muscle of streptozotocin-induced type 1 diabetic mice.","type":"article","volume":"290","mendeley_url":"http:\/\/www.mendeley.com\/research\/myostatin-induces-dna-damage-skeletal-muscle-streptozotocininduced-type-1-diabetic-mice-1"},"altmetric_score":{"score":9,"score_history":{"1y":0,"6m":0,"3m":0,"1m":0,"1w":0,"6d":0,"5d":0,"4d":0,"3d":0,"2d":0,"1d":0,"at":9},"context_for_score":{"all":{"total_number_of_other_articles":6771968,"mean":6.1646290473641,"rank":715394,"this_scored_higher_than_pct":88,"this_scored_higher_than":6022228,"rank_type":"exact","sample_size":6771968,"percentile":88},"similar_age_3m":{"total_number_of_other_articles":287505,"mean":8.6712838012688,"rank":41330,"this_scored_higher_than_pct":85,"this_scored_higher_than":245651,"rank_type":"exact","sample_size":287505,"percentile":85},"this_journal":{"total_number_of_other_articles":29296,"mean":3.0965638504864,"rank":852,"this_scored_higher_than_pct":96,"this_scored_higher_than":28352,"rank_type":"exact","sample_size":29296,"percentile":96},"similar_age_this_journal_3m":{"total_number_of_other_articles":449,"mean":5.393125,"rank":56,"this_scored_higher_than_pct":86,"this_scored_higher_than":388,"rank_type":"exact","sample_size":449,"percentile":86}}},"demographics":{"users":{"mendeley":{"by_status":{"Librarian":1},"by_discipline":{"Design":1}}}},"posts":{"blogs":[{"title":"Singapore investigation leads to two retractions, two more on the way","url":"http:\/\/retractionwatch.com\/2015\/12\/15\/singapore-investigation-leads-to-two-retractions-two-more-on-the-way\/","license":"public","citation_ids":[1053507,4879242,4879243],"posted_on":"2015-12-15T14:30:00+00:00","summary":"Authors have retracted papers from&nbsp;Cell Metabolism&nbsp;and the Journal of Biological Chemistry&nbsp;after an investigation in Singapore found issues, including falsified data. The investigation is ongoing, and two additional&nbsp;retractions, along w","author":{"name":"Retraction Watch","url":"http:\/\/retractionwatch.wordpress.com","description":"Tracking retractions as a window into the scientific process"}}]}}