{"altmetric_id":2474652,"counts":{"readers":{"mendeley":12,"citeulike":0,"connotea":0},"total":{"posts_count":2},"twitter":{"unique_users_count":2,"unique_users":["BlackPhysicists","CondensedPapers"],"posts_count":2}},"citation":{"altmetric_jid":"arxiv","arxiv_id":"1406.7016","first_seen_on":"2014-06-30T01:10:51+00:00","issns":[],"journal":"arXiv","last_mentioned_on":1404134541,"links":["http:\/\/arxiv.org\/abs\/1406.7016"],"pdf_url":"http:\/\/arxiv.org\/pdf\/1406.7016v1","pubdate":"2014-06-26T20:06:16+00:00","title":"Spin Supercurrent, Magnetization Dynamics, and Phi-State in\n  Spin-Textured Josephson Junctions","type":"article","mendeley_url":"http:\/\/www.mendeley.com\/research\/spin-supercurrent-magnetization-dynamics-%CF%86-state-spintextured-josephson-junctions"},"altmetric_score":{"score":0.5,"score_history":{"1y":0,"6m":0,"3m":0,"1m":0,"1w":0,"6d":0,"5d":0,"4d":0,"3d":0,"2d":0,"1d":0,"at":0.5},"context_for_score":{"all":{"total_number_of_other_articles":4505285,"mean":5.0995569853359,"rank":3164369,"this_scored_higher_than_pct":22,"this_scored_higher_than":1025396,"rank_type":"exact","sample_size":4505285,"percentile":22},"similar_age_3m":{"total_number_of_other_articles":107309,"mean":7.750747232266,"rank":73763,"this_scored_higher_than_pct":24,"this_scored_higher_than":26039,"rank_type":"exact","sample_size":107309,"percentile":24},"this_journal":{"total_number_of_other_articles":281989,"mean":2.55240667688,"rank":205634,"this_scored_higher_than_pct":14,"this_scored_higher_than":40134,"rank_type":"exact","sample_size":281989,"percentile":14},"similar_age_this_journal_3m":{"total_number_of_other_articles":5,"mean":5.512,"rank":4,"this_scored_higher_than_pct":1,"this_scored_higher_than":0,"rank_type":"exact","sample_size":5,"percentile":1}}},"demographics":{"poster_types":{"member_of_the_public":2},"users":{"twitter":{"cohorts":{"Members of the public":2}},"mendeley":{"by_status":{"Researcher":2,"Student  > Doctoral Student":1,"Student  > Ph. D. Student":6,"Student  > Postgraduate":1,"Student  > Master":2},"by_discipline":{"Materials Science":1,"Chemistry":1,"Physics and Astronomy":10}}},"geo":{"mendeley":{"CA":1,"ES":1}}},"posts":{"twitter":[{"url":"https:\/\/twitter.com\/BlackPhysicists\/status\/483601432990318592","license":"datasift","citation_ids":[2474652],"posted_on":"2014-06-30T13:22:21+00:00","author":{"name":"BlackPhysicists","image":"https:\/\/pbs.twimg.com\/profile_images\/502208695854313472\/mupwPlOC_normal.jpeg","id_on_source":"BlackPhysicists","tweeter_id":"46854930","geo":{"lt":null,"ln":null},"followers":16365},"tweet_id":"483601432990318592"},{"url":"https:\/\/twitter.com\/CondensedPapers\/status\/483417178486472704","license":"datasift","citation_ids":[2474652],"posted_on":"2014-06-30T01:10:11+00:00","author":{"name":"Condensed Matter","url":"http:\/\/arxiv.org\/archive\/cond-mat","image":"https:\/\/pbs.twimg.com\/profile_images\/1149878758\/arxiv_normal.png","description":"New Condensed Matter submissions to http:\/\/arxiv.org (not affiliated with http:\/\/arxiv.org)","id_on_source":"CondensedPapers","tweeter_id":"130343557","geo":{"lt":null,"ln":null},"followers":916},"tweet_id":"483417178486472704"}]}}