{"altmetric_id":20956834,"citation":{"aggregate_citation_ids":[],"attribution":"Google Books","authors_or_editors":["Luis Alfonso Escudero G\u00f3mez"],"first_seen_on":"2017-06-11T19:11:25+00:00","isbns":["9788484276258"],"issns":[],"last_mentioned_on":1497208274,"links":["https:\/\/books.google.com.py\/books?id=24_KRctvMNUC&pg=PA57&lpg=PA57&dq=las+nuevas+catedrales+los+shopping&source=bl&ots=teRDMRLPMT&sig=FB0xyF6o8dGLj_b9hzIqCDLrDJ4&hl=es&sa=X&ved=0ahUKEwiZi_rjvLbUAhVQOZAKHSG3AKUQ6AEILDAI#v=onepage&q=las%20nuevas%20catedrales%20los%20shopping&f=false"],"pubdate":"2008-01-01T00:00:00+00:00","publisher":"Univ de Castilla La Mancha","title":"Los centros comerciales, espacios postmodernos de ocio y de consumo","type":"book","uri":"http:\/\/books.google.com\/books?id=24_KRctvMNUC&hl=&source=gbs_api"},"altmetric_score":{"score":1,"score_history":{"1y":1,"6m":1,"3m":0,"1m":0,"1w":0,"6d":0,"5d":0,"4d":0,"3d":0,"2d":0,"1d":0,"at":1},"context_for_score":null},"demographics":{"poster_types":{"member_of_the_public":1},"users":{"twitter":{"cohorts":{"Members of the public":1}}}},"counts":{"total":{"posts_count":1},"twitter":{"unique_users_count":1,"unique_users":["MIRTHAGARCIA3"],"posts_count":1}},"posts":{"twitter":[{"url":"http:\/\/twitter.com\/MIRTHAGARCIA3\/statuses\/873980963742732288","license":"gnip","citation_ids":[20956834],"posted_on":"2017-06-11T19:11:14+00:00","author":{"name":"MIRTHA GARCIA","image":"https:\/\/abs.twimg.com\/sticky\/default_profile_images\/default_profile_normal.png","id_on_source":"MIRTHAGARCIA3","tweeter_id":"392762805","geo":{"lt":null,"ln":null},"followers":24},"tweet_id":"873980963742732288"}]}}