{"altmetric_id":202005,"counts":{"readers":{"mendeley":167,"citeulike":0,"connotea":0},"facebook":{"unique_users_count":1,"unique_users":["275513802463291"],"posts_count":1},"total":{"posts_count":16},"twitter":{"unique_users_count":11,"unique_users":["mellojonny","ShwetaDhawan1","NicholasCork","JakeMat91","akashkarki","DrChrisWilliams","brianrahmer","valeriemdaniel","buzhna","pohguk","ProfBambra"],"posts_count":15}},"selected_quotes":["#APHAwebinar Must engage in Healthy Public Policy advocacy - Push Towards a Politics of Health #HiAP","Motion 13 -so true health lies in all policy not just healthcare #ARMlive Great article explaining \u2026","@sarasiddiqui18 Ah, maybe coz it's a published article? Try this: Title:Towards a politics of health (Bambra et al.)","Motion 13 -so true health lies in all policy not just healthcare #ARMlive Great article from uni of liverpool"],"citation":{"abstract":"The importance of public policy as a determinant of health is routinely acknowledged, but there remains a continuing absence of mainstream debate about the ways in which the politics, power and ideology, which underpin public policy influence people's health. This paper explores the possible reasons behind the absence of a politics of health and demonstrates how explicit acknowledgement of the political nature of health will lead to more effective health promotion strategy and policy, and to more realistic and evidence-based public health and health promotion practice.","abstract_source":"pubmed","altmetric_jid":"4f6fa5253cf058f610003d1a","authors":["C. Bambra","Bambra C","Fox D","Scott-Samuel A","Bambra, Clare","Fox, Debbie","Scott-Samuel, Alex"],"doi":"10.1093\/heapro\/dah608","endpage":"193","first_seen_on":"2011-08-01T16:54:41+00:00","issns":["0957-4824","1460-2245"],"issue":"2","journal":"Health Promotion International","last_mentioned_on":1499149253,"links":["http:\/\/heapro.oxfordjournals.org\/content\/20\/2\/187.full","http:\/\/heapro.oxfordjournals.org\/content\/20\/2\/187.short","http:\/\/heapro.oxfordjournals.org\/content\/20\/2\/187.full.pdf+html","http:\/\/m.heapro.oxfordjournals.org\/content\/20\/2\/187.short","https:\/\/academic.oup.com\/heapro\/article-abstract\/20\/2\/187\/827479\/Towards-a-politics-of-health"],"pdf_url":"https:\/\/academic.oup.com\/heapro\/article-pdf\/20\/2\/187\/2467282\/dah608.pdf","pmid":"15722364","pubdate":"2005-02-18T00:00:00+00:00","publisher":"Sage","publisher_subjects":[{"name":"Public Health And Health Services","scheme":"era"},{"name":"Curriculum And Pedagogy","scheme":"era"}],"scopus_subjects":["Social Sciences","Medicine","Health Sciences"],"startpage":"187","subjects":["publichealth"],"title":"Towards a politics of health","type":"article","volume":"20","mendeley_url":"http:\/\/www.mendeley.com\/research\/towards-politics-health-9"},"altmetric_score":{"score":7.9,"score_history":{"1y":1.85,"6m":1.85,"3m":0,"1m":0,"1w":0,"6d":0,"5d":0,"4d":0,"3d":0,"2d":0,"1d":0,"at":7.9},"context_for_score":{"all":{"total_number_of_other_articles":8461697,"mean":7.1088157534769,"rank":1154142,"this_scored_higher_than_pct":86,"this_scored_higher_than":7305432,"rank_type":"exact","sample_size":8461697,"percentile":86},"similar_age_3m":{"total_number_of_other_articles":73755,"mean":6.1901440464246,"rank":11390,"this_scored_higher_than_pct":84,"this_scored_higher_than":62356,"rank_type":"exact","sample_size":73755,"percentile":84},"this_journal":{"total_number_of_other_articles":953,"mean":5.5651302521008,"rank":156,"this_scored_higher_than_pct":83,"this_scored_higher_than":797,"rank_type":"exact","sample_size":953,"percentile":83},"similar_age_this_journal_3m":{"total_number_of_other_articles":11,"mean":3.5198,"rank":2,"this_scored_higher_than_pct":81,"this_scored_higher_than":9,"rank_type":"exact","sample_size":11,"percentile":81}}},"demographics":{"poster_types":{"member_of_the_public":7,"researcher":1,"practitioner":2,"science_communicator":1},"users":{"twitter":{"cohorts":{"Practitioners (doctors, other healthcare professionals)":2,"Members of the public":7,"Science communicators (journalists, bloggers, editors)":1,"Scientists":1}},"mendeley":{"by_status":{"Unspecified":3,"Professor > Associate Professor":8,"Student  > Doctoral Student":14,"Researcher":18,"Student  > Ph. D. Student":31,"Student  > Postgraduate":13,"Student  > Master":43,"Other":7,"Student  > Bachelor":15,"Lecturer":7,"Lecturer > Senior Lecturer":2,"Professor":6},"by_discipline":{"Medicine and Dentistry":42,"Social Sciences":82,"Psychology":2,"Unspecified":7,"Environmental Science":3,"Arts and Humanities":5,"Engineering":2,"Earth and Planetary Sciences":2,"Economics, Econometrics and Finance":3,"Agricultural and Biological Sciences":6,"Computer Science":1,"Business, Management and Accounting":2,"Nursing and Health Professions":7,"Philosophy":3}}},"geo":{"twitter":{"GB":4,"CA":1,"US":4},"mendeley":{"SG":1,"CA":4,"US":4,"IE":1,"BR":1,"IT":1,"GB":8,"AU":1,"PT":2,"DE":1,"ES":1}}},"posts":{"twitter":[{"url":"http:\/\/twitter.com\/#!\/mellojonny\/status\/98048827298299904","citation_ids":[202005],"posted_on":"2011-08-01T15:13:56+00:00","author":{"name":"#hellomynameis JT","url":"https:\/\/abetternhs.wordpress.com\/","image":"https:\/\/pbs.twimg.com\/profile_images\/640081318991130624\/xTXOA1bb_normal.png","description":"Jonathon Tomlinson. East London GP, Trauma-informed care, chronic pain, medical education, patient-advocacy. Cyclist. Dad.","id_on_source":"mellojonny","tweeter_id":"65575742","geo":{"lt":51.53333,"ln":-0.08333,"country":"GB"},"followers":12822},"tweet_id":"98048827298299904"},{"url":"http:\/\/twitter.com\/#!\/mellojonny\/status\/104244292234657793","citation_ids":[202005],"posted_on":"2011-08-18T17:32:30+00:00","author":{"name":"#hellomynameis JT","url":"https:\/\/abetternhs.wordpress.com\/","image":"https:\/\/pbs.twimg.com\/profile_images\/640081318991130624\/xTXOA1bb_normal.png","description":"Jonathon Tomlinson. East London GP, Trauma-informed care, chronic pain, medical education, patient-advocacy. Cyclist. Dad.","id_on_source":"mellojonny","tweeter_id":"65575742","geo":{"lt":51.53333,"ln":-0.08333,"country":"GB"},"followers":12822},"tweet_id":"104244292234657793"},{"url":"http:\/\/twitter.com\/ShwetaDhawan1\/status\/390600745084416000","license":"public","citation_ids":[202005],"posted_on":"2013-10-16T22:10:49+00:00","author":{"name":"Shweta Dhawan","image":"https:\/\/pbs.twimg.com\/profile_images\/464822764273029120\/SKM9ahNg_normal.jpeg","description":"MD candidate, @DalMedSchool | MPH Epidemiology, @UofAPublicHealth | Co-director, @MentorNet_CSIH | Tweets about #health, #healthcare, #education | Views my own","id_on_source":"ShwetaDhawan1","tweeter_id":"776858251","geo":{"lt":44.64533,"ln":-63.57239,"country":"CA"},"followers":502},"tweet_id":"390600745084416000"},{"url":"http:\/\/twitter.com\/NicholasCork\/status\/462192908431802368","license":"datasift","citation_ids":[202005],"posted_on":"2014-05-02T11:32:31+00:00","author":{"name":"Dr Nick Manning-Cork","url":"http:\/\/uk.linkedin.com\/pub\/nick-cork\/4b\/684\/a52","image":"https:\/\/pbs.twimg.com\/profile_images\/532937803231805441\/cuwxXZvs_normal.jpeg","description":"Healthcare Innovation & Improvement. Associate @GMCuk. TEF Assessor @HEFCE. Associate Editor: @BMJOpenQuality & @Clin_Med @RCPLondon. @Cambridge_Uni Dr @EKHUFT","id_on_source":"NicholasCork","tweeter_id":"23690324","geo":{"lt":51.50853,"ln":-0.12574,"country":"GB"},"followers":1201},"tweet_id":"462192908431802368"},{"url":"http:\/\/twitter.com\/JakeMat91\/status\/462855417513906176","license":"datasift","rt":["NicholasCork"],"citation_ids":[202005],"posted_on":"2014-05-04T07:25:05+00:00","author":{"name":"Jake Matthews","url":"http:\/\/jakemat91.wordpress.com","image":"https:\/\/pbs.twimg.com\/profile_images\/589407672044163072\/e21Nx0lh_normal.png","description":"Brum based doctor","id_on_source":"JakeMat91","tweeter_id":"1926803696","geo":{"lt":33.52066,"ln":-86.80249,"country":"US"},"followers":704},"tweet_id":"462855417513906176"},{"url":"http:\/\/twitter.com\/akashkarki\/statuses\/329524776987140097","license":"public","citation_ids":[202005],"posted_on":"2013-05-01T09:16:43+00:00","author":{"name":"Akash Karki","image":"https:\/\/pbs.twimg.com\/profile_images\/806929405541052416\/TJRzyNFI_normal.jpg","description":"Now not so recently qualified GP. Past Darzi Fellow. Here to listen.Interested to learn about the thinking behind the thinking.Tweets in personal capacity.","id_on_source":"akashkarki","tweeter_id":"22698775","geo":{"lt":36.72821,"ln":-76.58356,"country":"US"},"followers":521},"tweet_id":"329524776987140097"},{"url":"https:\/\/twitter.com\/akashkarki\/status\/612925413673816064","license":"datasift","citation_ids":[202005],"posted_on":"2015-06-22T10:09:40+00:00","author":{"name":"Akash Karki","image":"https:\/\/pbs.twimg.com\/profile_images\/806929405541052416\/TJRzyNFI_normal.jpg","description":"Now not so recently qualified GP. Past Darzi Fellow. Here to listen.Interested to learn about the thinking behind the thinking.Tweets in personal capacity.","id_on_source":"akashkarki","tweeter_id":"22698775","geo":{"lt":36.72821,"ln":-76.58356,"country":"US"},"followers":521},"tweet_id":"612925413673816064"},{"url":"https:\/\/twitter.com\/akashkarki\/status\/612924616370188288","license":"datasift","citation_ids":[202005],"posted_on":"2015-06-22T10:06:30+00:00","author":{"name":"Akash Karki","image":"https:\/\/pbs.twimg.com\/profile_images\/806929405541052416\/TJRzyNFI_normal.jpg","description":"Now not so recently qualified GP. Past Darzi Fellow. Here to listen.Interested to learn about the thinking behind the thinking.Tweets in personal capacity.","id_on_source":"akashkarki","tweeter_id":"22698775","geo":{"lt":36.72821,"ln":-76.58356,"country":"US"},"followers":521},"tweet_id":"612924616370188288"},{"url":"https:\/\/twitter.com\/DrChrisWilliams\/status\/612926492759228417","license":"datasift","rt":["akashkarki"],"citation_ids":[202005],"posted_on":"2015-06-22T10:13:58+00:00","author":{"name":"Chris Williams","image":"https:\/\/pbs.twimg.com\/profile_images\/3576575576\/31394bca6b0a4c4ef8623920ae309a03_normal.jpeg","description":"GP, clinical educator, cyclist. Involved with my LMC, BMA, RCGP in the quest for better health & social care. Any views are personal. RTs \u2260 endorsement.","id_on_source":"DrChrisWilliams","tweeter_id":"336474525","geo":{"lt":56,"ln":-4,"country":"GB"},"followers":1669},"tweet_id":"612926492759228417"},{"url":"https:\/\/twitter.com\/brianrahmer\/status\/628636167030898690","license":"datasift","citation_ids":[202005],"posted_on":"2015-08-04T18:38:36+00:00","author":{"name":"Brian Rahmer","url":"https:\/\/goo.gl\/ZllurF","image":"https:\/\/pbs.twimg.com\/profile_images\/718894088855121920\/qqi1FiIw_normal.jpg","description":"Dad to three, connecting the dots. #HiAP #SDoH Power, Politics, Privilege, & The People's Health. Views are mine.","id_on_source":"brianrahmer","tweeter_id":"17809655","geo":{"lt":39.00039,"ln":-75.49992,"country":"US"},"followers":7852},"tweet_id":"628636167030898690"},{"url":"https:\/\/twitter.com\/valeriemdaniel\/status\/628636421289574400","license":"datasift","rt":["brianrahmer"],"citation_ids":[202005],"posted_on":"2015-08-04T18:39:36+00:00","author":{"name":"Valerie Daniel","image":"https:\/\/pbs.twimg.com\/profile_images\/756160351834632193\/MlOkl34R_normal.jpg","description":"Health communicator working to help others make positive behavior changes. Social media addict, new mom & foodie. Tweets are my opinion only.","id_on_source":"valeriemdaniel","tweeter_id":"108666660","geo":{"lt":33.749,"ln":-84.38798,"country":"US"},"followers":287},"tweet_id":"628636421289574400"},{"url":"http:\/\/twitter.com\/brianrahmer\/statuses\/749717738310938624","license":"gnip","citation_ids":[202005],"posted_on":"2016-07-03T21:33:32+00:00","author":{"name":"Brian Rahmer","url":"https:\/\/goo.gl\/ZllurF","image":"https:\/\/pbs.twimg.com\/profile_images\/718894088855121920\/qqi1FiIw_normal.jpg","description":"Dad to three, connecting the dots. #HiAP #SDoH Power, Politics, Privilege, & The People's Health. Views are mine.","id_on_source":"brianrahmer","tweeter_id":"17809655","geo":{"lt":39.00039,"ln":-75.49992,"country":"US"},"followers":7852},"tweet_id":"749717738310938624"},{"url":"http:\/\/twitter.com\/buzhna\/statuses\/881999263735197696","license":"gnip","rt":["brianrahmer"],"citation_ids":[202005],"posted_on":"2017-07-03T22:13:05+00:00","author":{"name":"Alex Scott-Samuel","image":"https:\/\/pbs.twimg.com\/profile_images\/509379218976014336\/fGIA-0Td_normal.jpeg","description":"\u262epolitics as if people mattered\u262e","id_on_source":"buzhna","tweeter_id":"253665125","geo":{"lt":null,"ln":null},"followers":1219},"tweet_id":"881999263735197696"},{"url":"http:\/\/twitter.com\/pohguk\/statuses\/881999742682660864","license":"gnip","rt":["brianrahmer"],"citation_ids":[202005],"posted_on":"2017-07-03T22:15:00+00:00","author":{"name":"PoliticsOfHealthGp","url":"http:\/\/www.pohg.org.uk\/","image":"https:\/\/pbs.twimg.com\/profile_images\/552869797822603264\/REZgoMsZ_normal.jpeg","description":"Speaking out and campaigning on the health impact of politics and power","id_on_source":"pohguk","tweeter_id":"2966096351","geo":{"lt":null,"ln":null},"followers":388},"tweet_id":"881999742682660864"},{"url":"http:\/\/twitter.com\/ProfBambra\/statuses\/882122022914060288","license":"gnip","rt":["brianrahmer"],"citation_ids":[202005],"posted_on":"2017-07-04T06:20:53+00:00","author":{"name":"Prof Clare L Bambra","url":"http:\/\/www.ncl.ac.uk\/ihs\/staff\/profile\/clarebambra.html#background","image":"https:\/\/pbs.twimg.com\/profile_images\/814772347202895872\/0ny_Ljyh_normal.jpg","description":"Professor of Public Health @UniofNewcastle | @Fuse_Online | #healthinequality | #publichealth | #SDoH | #HiAP | Personal capacity.","id_on_source":"ProfBambra","tweeter_id":"338447876","geo":{"lt":52.16045,"ln":-0.70312,"country":"GB"},"followers":1865},"tweet_id":"882122022914060288"}],"facebook":[{"title":"Towards a politics of health","url":"https:\/\/www.facebook.com\/permalink.php?story_fbid=106735932787970&id=275513802463291","citation_ids":[202005],"posted_on":"2012-02-11T18:03:47+00:00","summary":"Power is an important public health issue!","author":{"name":"Enrique Cardiel","url":"https:\/\/www.facebook.com\/275513802463291","facebook_wall_name":"New Mexico Public Health Association","image":"https:\/\/graph.facebook.com\/275513802463291\/picture","id_on_source":"275513802463291"}}]}}