{"altmetric_id":8615474,"citation":{"aggregate_citation_ids":[],"authors":["Louise LEstrange Fawcett"],"first_seen_on":"2016-06-09T18:41:57+00:00","isbns":["9780521104739"],"issns":[],"last_mentioned_on":1465493700,"links":["http:\/\/www.cambridge.org\/us\/academic\/subjects\/politics-international-relations\/international-relations-and-international-organisations\/iran-and-cold-war-azerbaijan-crisis-1946"],"pubdate":"2009-03-19T00:00:00+00:00","publisher":"Cambridge University Press","title":"Iran and the Cold War","type":"book"},"altmetric_score":{"score":5,"score_history":{"1y":0,"6m":0,"3m":0,"1m":0,"1w":0,"6d":0,"5d":0,"4d":0,"3d":0,"2d":0,"1d":0,"at":5},"context_for_score":null},"demographics":[],"counts":{"total":{"posts_count":1},"blogs":{"unique_users_count":1,"unique_users":[56575],"posts_count":1}},"posts":{"blogs":[{"title":"Interview \u2013 Louise Fawcett","url":"http:\/\/www.e-ir.info\/2016\/06\/09\/interview-louise-fawcett\/","license":"public","citation_ids":[8615473,8615474,8615477,1293723,8615481],"posted_on":"2016-06-09T17:35:00+00:00","summary":"Louise Fawcett discusses the resurgence of regionalism, the long-term effects of the Iraq War, and elaborates on why Iran should be considered an aspiring regional power.","author":{"name":"E-International Relations","url":"http:\/\/www.e-ir.info\/","description":"the world&rsquo;s leading website for students and scholars of international politics"}}]}}