{"altmetric_id":7193239,"counts":{"readers":{"mendeley":0,"citeulike":0,"connotea":0},"total":{"posts_count":2},"twitter":{"unique_users_count":1,"unique_users":["JCENJournal"],"posts_count":1},"facebook":{"unique_users_count":1,"unique_users":["197530227024210"],"posts_count":1}},"selected_quotes":["Earn 1.2 contact hours by completing our #CNE activity about population-focused care #JCEN"],"citation":{"altmetric_jid":"4f6fa5e93cf058f610005a1c","doi":"10.3928\/00220124-20160419-07","endpage":"221","first_seen_on":"2016-05-05T20:06:32+00:00","funders":["niehs"],"issns":["0022-0124","1938-2472"],"issue":"5","journal":"Journal of Continuing Education in Nursing","last_mentioned_on":1463058157,"links":["http:\/\/www.healio.com\/nursing\/journals\/jcen\/2016-5-47-5\/%7B4e1e5280-78e2-47ac-9471-e080f233cc88%7D\/cne-quiz-population-focused-practice-competency-needs-among-public-health-nursing-leaders-in-washington-state","http:\/\/www.healio.com\/nursing\/journals\/jcen\/2016-5-47-5\/%7B4e1e5280-78e2-47ac-9471-e080f233cc88%7D\/cne-quiz-population-focused-practice-competency-needs-among-public-health-nursing-leaders-in-washington-state?platform=hootsuite"],"pdf_url":"http:\/\/www.healio.com\/nursing\/journals\/jcen\/2016-5-47-5\/{4e1e5280-78e2-47ac-9471-e080f233cc88}\/cne-quiz-population-focused-practice-competency-needs-among-public-health-nursing-leaders-in-washington-state.pdf","pmid":"27124076","pubdate":"2016-04-30T00:00:00+00:00","publisher":"SLACK Incorporated","publisher_subjects":[{"name":"Nursing","scheme":"era"},{"name":"Education Systems","scheme":"era"}],"scopus_subjects":["Health Sciences","Nursing"],"startpage":"220","subjects":["nursing","education"],"title":"CNE Quiz: Population-Focused Practice Competency Needs Among Public Health Nursing Leaders in Washington State","type":"article","volume":"47"},"altmetric_score":{"score":0.75,"score_history":{"1y":0,"6m":0,"3m":0,"1m":0,"1w":0,"6d":0,"5d":0,"4d":0,"3d":0,"2d":0,"1d":0,"at":0.75},"context_for_score":{"all":{"total_number_of_other_articles":7690302,"mean":6.5973724521265,"rank":5541042,"this_scored_higher_than_pct":24,"this_scored_higher_than":1874440,"rank_type":"exact","sample_size":7690302,"percentile":24},"similar_age_3m":{"total_number_of_other_articles":266736,"mean":11.386076615367,"rank":171406,"this_scored_higher_than_pct":29,"this_scored_higher_than":79899,"rank_type":"exact","sample_size":266736,"percentile":29},"this_journal":{"total_number_of_other_articles":178,"mean":1.6769378531073,"rank":98,"this_scored_higher_than_pct":42,"this_scored_higher_than":75,"rank_type":"exact","sample_size":178,"percentile":42},"similar_age_this_journal_3m":{"total_number_of_other_articles":24,"mean":0.98695652173913,"rank":8,"this_scored_higher_than_pct":62,"this_scored_higher_than":15,"rank_type":"exact","sample_size":24,"percentile":62}}},"demographics":{"poster_types":{"member_of_the_public":1},"users":{"twitter":{"cohorts":{"Members of the public":1}}},"geo":{"twitter":{"US":1}}},"posts":{"facebook":[{"title":"CNE Quiz: Population-Focused Practice Competency Needs Among Public Health Nursing Leaders in...","url":"https:\/\/www.facebook.com\/permalink.php?story_fbid=868033409973885&id=197530227024210","license":"public","citation_ids":[7193239],"posted_on":"2016-05-03T14:09:10+00:00","summary":"Earn 1.2 contact hours by taking JCEN's CNE quiz. The topic for May is Population-Focused Practice Competency Needs Among Public Health Nursing Leaders in Washington.","author":{"name":"Slack Nursing Journals","url":"https:\/\/www.facebook.com\/197530227024210","facebook_wall_name":"Slack Nursing Journals","image":"https:\/\/graph.facebook.com\/197530227024210\/picture","id_on_source":"197530227024210"}}],"twitter":[{"url":"http:\/\/twitter.com\/JCENJournal\/statuses\/730744991274897408","license":"gnip","citation_ids":[7193239],"posted_on":"2016-05-12T13:02:37+00:00","author":{"name":"JCENJournal","url":"http:\/\/www.healio.com\/JCEN","image":"https:\/\/pbs.twimg.com\/profile_images\/545939010288226304\/qYTW8V4S_normal.jpeg","description":"Articles on continuing nursing education and staff development.","id_on_source":"JCENJournal","tweeter_id":"95928739","geo":{"lt":40.16706,"ln":-74.49987,"country":"US"},"followers":1191},"tweet_id":"730744991274897408"}]}}