{"altmetric_id":23930552,"citation":{"aggregate_citation_ids":[],"attribution":"Google Books","authors_or_editors":["Carl J. Richard"],"first_seen_on":"2017-08-16T23:03:02+00:00","isbns":["9780742567801"],"issns":[],"last_mentioned_on":1502904840,"links":["https:\/\/books.google.com\/books?id=dlMr4UhqQlQC&pg=PA29&lpg=PA29&dq=romans+sent+slaves+to+clean+sewers&source=bl&ots=UTI41vsqGI&sig=XDrgQI2p3gNuvRR_iWDZhFXLTCI&hl=en&sa=X&ved=0ahUKEwiL0Z2W4dXVAhUJwlQKHRktCGkQ6AEIRzAF"],"pubdate":"2010-04-16T00:00:00+00:00","publisher":"Rowman & Littlefield Publishers","title":"Why We're All Romans","type":"book","uri":"http:\/\/books.google.com\/books?id=dlMr4UhqQlQC&hl=&source=gbs_api"},"altmetric_score":{"score":9,"score_history":{"1y":9,"6m":9,"3m":9,"1m":0,"1w":0,"6d":0,"5d":0,"4d":0,"3d":0,"2d":0,"1d":0,"at":9},"context_for_score":null},"demographics":[],"counts":{"total":{"posts_count":1},"blogs":{"unique_users_count":1,"unique_users":[52322],"posts_count":1}},"posts":{"blogs":[{"title":"Huge Blobs of Fat and Trash Are Filling the World\u2019s Sewers","url":"http:\/\/news.nationalgeographic.com\/2017\/08\/fatbergs-fat-cities-sewers-wet-wipes-science\/","license":"public","citation_ids":[23930552,2988712,1545559],"posted_on":"2017-08-16T17:34:00+00:00","summary":"","author":{"name":"Phenomena \u00bb The Loom","url":"http:\/\/phenomena.nationalgeographic.com\/blog\/the-loom\/","description":"A science salon hosted by National Geographic Magazine"}}]}}